golemdb_sql/__init__.py
golemdb_sql/connection.py
golemdb_sql/connection_parser.py
golemdb_sql/cursor.py
golemdb_sql/exceptions.py
golemdb_sql/filters.py
golemdb_sql/query_translator.py
golemdb_sql/row_serializer.py
golemdb_sql/schema_manager.py
golemdb_sql/types.py
golemdb_sql-0.1.0.dist-info/METADATA
golemdb_sql-0.1.0.dist-info/WHEEL
golemdb_sql-0.1.0.dist-info/RECORD
