Metadata-Version: 2.3
Name: golemdb-sql
Version: 0.1.0
Summary: PEP 249 compliant DB-API 2.0 implementation for GolemBase
License: MIT
Author: Your Name
Author-email: your.email@example.com
Requires-Python: >=3.10,<4.0
Classifier: Development Status :: 3 - Alpha
Classifier: Intended Audience :: Developers
Classifier: License :: OSI Approved :: MIT License
Classifier: Programming Language :: Python :: 3
Classifier: Programming Language :: Python :: 3.10
Classifier: Programming Language :: Python :: 3.11
Classifier: Programming Language :: Python :: 3.12
Classifier: Programming Language :: Python :: 3.13
Classifier: Topic :: Database
Classifier: Topic :: Database :: Database Engines/Servers
Classifier: Topic :: Software Development :: Libraries :: Python Modules
Requires-Dist: appdirs (>=1.4.4,<2.0.0)
Requires-Dist: golem-base-sdk (==0.1.0)
Requires-Dist: python-dotenv (>=1.1.1,<2.0.0)
Requires-Dist: sqlglot (>=20.0.0,<21.0.0)
Requires-Dist: toml (>=0.10.2,<0.11.0)
